odoo8_addon_connector_job_subscribe-8.0.1.0.0.99.dev13-py3.8-nspkg.pth
odoo_addons/connector_job_subscribe/README.rst
odoo_addons/connector_job_subscribe/__init__.py
odoo_addons/connector_job_subscribe/__openerp__.py
odoo_addons/connector_job_subscribe/i18n/ar.po
odoo_addons/connector_job_subscribe/i18n/bg.po
odoo_addons/connector_job_subscribe/i18n/ca.po
odoo_addons/connector_job_subscribe/i18n/connector_job_subscribe.pot
odoo_addons/connector_job_subscribe/i18n/da.po
odoo_addons/connector_job_subscribe/i18n/de.po
odoo_addons/connector_job_subscribe/i18n/el_GR.po
odoo_addons/connector_job_subscribe/i18n/es.po
odoo_addons/connector_job_subscribe/i18n/fi.po
odoo_addons/connector_job_subscribe/i18n/fr.po
odoo_addons/connector_job_subscribe/i18n/fr_CH.po
odoo_addons/connector_job_subscribe/i18n/hr.po
odoo_addons/connector_job_subscribe/i18n/hr_HR.po
odoo_addons/connector_job_subscribe/i18n/hu.po
odoo_addons/connector_job_subscribe/i18n/it.po
odoo_addons/connector_job_subscribe/i18n/nl.po
odoo_addons/connector_job_subscribe/i18n/pt_BR.po
odoo_addons/connector_job_subscribe/i18n/sl.po
odoo_addons/connector_job_subscribe/i18n/tr.po
odoo_addons/connector_job_subscribe/i18n/tr_TR.po
odoo_addons/connector_job_subscribe/i18n/zh_CN.po
odoo_addons/connector_job_subscribe/models/__init__.py
odoo_addons/connector_job_subscribe/models/res_users.py
odoo_addons/connector_job_subscribe/queue/__init__.py
odoo_addons/connector_job_subscribe/queue/model.py
odoo_addons/connector_job_subscribe/static/description/icon.png
odoo_addons/connector_job_subscribe/tests/__init__.py
odoo_addons/connector_job_subscribe/tests/test_job_subscribe.py
odoo_addons/connector_job_subscribe/views/res_users_view.xml
odoo8_addon_connector_job_subscribe-8.0.1.0.0.99.dev13.dist-info/METADATA
odoo8_addon_connector_job_subscribe-8.0.1.0.0.99.dev13.dist-info/WHEEL
odoo8_addon_connector_job_subscribe-8.0.1.0.0.99.dev13.dist-info/namespace_packages.txt
odoo8_addon_connector_job_subscribe-8.0.1.0.0.99.dev13.dist-info/top_level.txt
odoo8_addon_connector_job_subscribe-8.0.1.0.0.99.dev13.dist-info/RECORD
